setup.py
brod/__init__.py
brod/base.py
brod/blocking.py
brod/nonblocking.py
brod/simple.py
brod/util.py
brod/zk.py
brod.egg-info/PKG-INFO
brod.egg-info/SOURCES.txt
brod.egg-info/dependency_links.txt
brod.egg-info/entry_points.txt
brod.egg-info/requires.txt
brod.egg-info/top_level.txt
brod.egg-info/zip-safe